pyntfy/__init__.py
pyntfy/action.py
pyntfy/notification.py
pyntfy/actions/__init__.py
pyntfy/actions/broadcastaction.py
pyntfy/actions/httpaction.py
pyntfy/actions/viewaction.py
pyntfy-0.2.1.dist-info/LICENSE
pyntfy-0.2.1.dist-info/METADATA
pyntfy-0.2.1.dist-info/WHEEL
pyntfy-0.2.1.dist-info/top_level.txt
pyntfy-0.2.1.dist-info/RECORD
